pyminer_algorithms_document_server/__init__.py
pyminer_algorithms_document_server/renderer.py
pyminer_algorithms_document_server/server.py
pyminer_algorithms_document_server/static/main.css
pyminer_algorithms_document_server/static/main.css.map
pyminer_algorithms_document_server/templates/content.html
pyminer_algorithms_document_server-0.0.5.dist-info/LICENSE
pyminer_algorithms_document_server-0.0.5.dist-info/METADATA
pyminer_algorithms_document_server-0.0.5.dist-info/WHEEL
pyminer_algorithms_document_server-0.0.5.dist-info/top_level.txt
pyminer_algorithms_document_server-0.0.5.dist-info/RECORD
