Metadata-Version: 2.1
Name: pyminer-algorithms-document-server
Version: 0.0.5
Summary: A small documentation server for PyMiner
Home-page: https://gitee.com/py2cn/pyminer-algorithms-document-server
Author: panhaoyu
Author-email: panhaoyu.china@outlook.com
License: UNKNOWN
Platform: UNKNOWN
Classifier: Programming Language :: Python :: 3
Classifier: License :: OSI Approved :: MIT License
Classifier: Operating System :: OS Independent
Requires-Python: >=3.8
Requires-Dist: flask
Requires-Dist: markdown
Requires-Dist: waitress
